syllabus/__init__.py
syllabus/models.py
syllabus/py.typed
syllabus/sync.py
syllabus/util.py
syllabus/where.py
syllabus/cli/main.py
jtl_syllabus-1.20250530.2.dist-info/METADATA
jtl_syllabus-1.20250530.2.dist-info/WHEEL
jtl_syllabus-1.20250530.2.dist-info/entry_points.txt
jtl_syllabus-1.20250530.2.dist-info/RECORD
